little_timmy/__init__.py
little_timmy/__main__.py
little_timmy/config_loader.py
little_timmy/duplicated_var_finder.py
little_timmy/taml.py
little_timmy/unused_var_finder.py
little_timmy/utils.py
little_timmy-3.5.0.dist-info/licenses/LICENSE
little_timmy-3.5.0.dist-info/METADATA
little_timmy-3.5.0.dist-info/WHEEL
little_timmy-3.5.0.dist-info/entry_points.txt
little_timmy-3.5.0.dist-info/top_level.txt
little_timmy-3.5.0.dist-info/RECORD
