Metadata-Version: 2.4
Name: little-timmy
Version: 3.5.0
Summary: Little Timmy will try their best to find those unused and duplicated Ansible variables.
Author: Huw
License: MIT License
Project-URL: Homepage, https://github.com/hoo29/little-timmy
Requires-Python: >=3.9
License-File: LICENSE
Requires-Dist: ansible>=3.0.0
Requires-Dist: jsonschema>=4.18.5
Provides-Extra: tests
Requires-Dist: pytest; extra == "tests"
Provides-Extra: build
Requires-Dist: build; extra == "build"
Dynamic: license-file
